mtsort.py
mtsort-1.0.1.dist-info/METADATA
mtsort-1.0.1.dist-info/RECORD
mtsort-1.0.1.dist-info/WHEEL
mtsort-1.0.1.dist-info/entry_points.txt
mtsort-1.0.1.dist-info/top_level.txt
