Metadata-Version: 2.1
Name: mtsort
Version: 1.0.1
Summary: A cross-platform module for sorting files by time.
Home-page: https://github.com/stiftcast/mtsort
Author: stiftcast
Author-email: stiftcast@gmail.com
License: MIT
Platform: UNKNOWN
Classifier: Programming Language :: Python :: 3.5
Classifier: Programming Language :: Python :: 3.6
Classifier: Programming Language :: Python :: 3.7
Classifier: License :: OSI Approved :: MIT License
Classifier: Operating System :: OS Independent
